yagocd/__init__.py
yagocd/client.py
yagocd/exception.py
yagocd/session.py
yagocd/util.py
yagocd/resources/__init__.py
yagocd/resources/agent.py
yagocd/resources/artifact.py
yagocd/resources/configuration.py
yagocd/resources/elastic_profile.py
yagocd/resources/encryption.py
yagocd/resources/environment.py
yagocd/resources/feed.py
yagocd/resources/info.py
yagocd/resources/job.py
yagocd/resources/material.py
yagocd/resources/package.py
yagocd/resources/package_repository.py
yagocd/resources/pipeline.py
yagocd/resources/pipeline_config.py
yagocd/resources/plugin_info.py
yagocd/resources/property.py
yagocd/resources/scm.py
yagocd/resources/stage.py
yagocd/resources/template.py
yagocd/resources/user.py
yagocd/resources/version.py
yagocd-1.0.1.dist-info/DESCRIPTION.rst
yagocd-1.0.1.dist-info/METADATA
yagocd-1.0.1.dist-info/metadata.json
yagocd-1.0.1.dist-info/RECORD
yagocd-1.0.1.dist-info/top_level.txt
yagocd-1.0.1.dist-info/WHEEL
