Metadata-Version: 2.0
Name: yagocd
Version: 1.0.1
Summary: Yet another Python client for ThoughtWorks GoCD REST API.
Home-page: https://github.com/grundic/yagocd
Author: Grigory Chernyshev
Author-email: systray@yandex.ru
License: MIT
Keywords: yagocd
Platform: UNKNOWN
Classifier: Development Status :: 2 - Pre-Alpha
Classifier: Intended Audience :: Developers
Classifier: License :: OSI Approved :: ISC License (ISCL)
Classifier: Natural Language :: English
Classifier: Programming Language :: Python :: 2
Classifier: Programming Language :: Python :: 2.6
Classifier: Programming Language :: Python :: 2.7
Classifier: Programming Language :: Python :: 3
Classifier: Programming Language :: Python :: 3.3
Classifier: Programming Language :: Python :: 3.4
Classifier: Programming Language :: Python :: 3.5
Requires-Dist: six
Requires-Dist: requests
Requires-Dist: easydict
